wikitablescrape/__init__.py
wikitablescrape/__main__.py
wikitablescrape/cli.py
wikitablescrape/parse.py
wikitablescrape/test_parse.py
wikitablescrape-1.0.4.data/scripts/wikitablescrape
wikitablescrape-1.0.4.dist-info/LICENSE
wikitablescrape-1.0.4.dist-info/METADATA
wikitablescrape-1.0.4.dist-info/WHEEL
wikitablescrape-1.0.4.dist-info/top_level.txt
wikitablescrape-1.0.4.dist-info/RECORD
