Metadata-Version: 2.1
Name: wikitablescrape
Version: 1.0.4
Summary: Scrape HTML tables from a Wikipedia page into CSV format.
Home-page: https://github.com/rocheio/wiki-table-scrape
Author: Andy Roche
Author-email: andy@roche.io
License: UNKNOWN
Platform: UNKNOWN
Classifier: Programming Language :: Python :: 3
Classifier: License :: OSI Approved :: MIT License
Classifier: Operating System :: OS Independent
Requires-Dist: beautifulsoup4 (==4.*)
Requires-Dist: lxml (==4.*)
Requires-Dist: requests (==2.*)
